<?xml version="1.0"?>
<!DOCTYPE hibernate-mapping PUBLIC "-//Hibernate/Hibernate Mapping DTD 3.0//EN"
"http://www.hibernate.org/dtd/hibernate-mapping-3.0.dtd">
<!-- Generated 31-oct-2015 11:05:47 by Hibernate Tools 4.3.1.Final -->
<hibernate-mapping>
    <class name="co.weepa.smile.contabilidad.dto.DefiConceptoRf" table="defi_concepto_rf" catalog="weepa">
        <id name="idconceptorf" type="int">
            <column name="IDCONCEPTORF" />
            <generator class="assigned" />
        </id>
        <property name="dsconcepto" type="string">
            <column name="DSCONCEPTO" length="100" />
        </property>
        <property name="dsdescripcion" type="string">
            <column name="DSDESCRIPCION" length="200" />
        </property>
    </class>
</hibernate-mapping>
